flutter_driver/__init__.py
flutter_driver/command.py
flutter_driver/driver.py
flutter_driver/jsonrpc.py
flutter_driver/runner.py
flutter_driver-1.0.9.dist-info/LICENSE.txt
flutter_driver-1.0.9.dist-info/METADATA
flutter_driver-1.0.9.dist-info/WHEEL
flutter_driver-1.0.9.dist-info/top_level.txt
flutter_driver-1.0.9.dist-info/RECORD
