Metadata-Version: 2.1
Name: flutter-driver
Version: 1.0.9
Summary: An flutter automation driver for python
Home-page: https://github.com/183181731/flutter-driver
Author: ndaeqa-wang
Author-email: 183181731@qq.com
License: MIT
Keywords: flutter windows,python client,ui automation
Platform: UNKNOWN
Classifier: Development Status :: 5 - Production/Stable
Classifier: Programming Language :: Python
Classifier: Programming Language :: Python :: 3.7
Classifier: Programming Language :: Python :: 3.8
Classifier: Programming Language :: Python :: 3.9
Classifier: Environment :: Console
Classifier: Environment :: MacOS X
Classifier: Environment :: Win32 (MS Windows)
Classifier: Intended Audience :: Developers
Classifier: Intended Audience :: Other Audience
Classifier: License :: OSI Approved :: MIT License
Classifier: Operating System :: OS Independent
Classifier: Topic :: Software Development :: Quality Assurance
Classifier: Topic :: Software Development :: Testing
License-File: LICENSE.txt
Requires-Dist: aiohttp
Requires-Dist: jsonrpc-base
Requires-Dist: pywinauto
